LICENSE
README.md
pyproject.toml
setup.py
g2m_snowflake_sdk_python.egg-info/PKG-INFO
g2m_snowflake_sdk_python.egg-info/SOURCES.txt
g2m_snowflake_sdk_python.egg-info/dependency_links.txt
g2m_snowflake_sdk_python.egg-info/top_level.txt
g2mclient/__init__.py
g2mclient/analyzer.py
g2mclient/client_basic_auth.py
g2mclient/client_snowflake_auth.py
g2mclient/constants.py
g2mclient/runner_base.py
g2mclient/runner_causal.py
g2mclient/runner_cluster.py
g2mclient/runner_mmm.py
g2mclient/runner_performance.py
g2mclient/runner_propensity.py
g2mclient/runner_regression.py
g2mclient/runner_task.py
g2mclient/snowflake_keypair_auth.py
g2mclient/utils.py
tests/test_all.py
tests/test_quick.py