Metadata-Version: 2.2
Name: g2m-snowflake-sdk-python
Version: 1.0.10
Summary: Python SDK for the G2M Platform API
Home-page: https://github.com/g2mai/g2m-snowflake-sdk-python
Author: G2M Team
Author-email: support@g2m.ai
License: Apache 2.0
Classifier: Programming Language :: Python :: 3
Classifier: Programming Language :: Python :: 3.7
Classifier: Programming Language :: Python :: 3.8
Classifier: Programming Language :: Python :: 3.9
Classifier: Programming Language :: Python :: 3.10
Classifier: Programming Language :: Python :: 3.11
License-File: LICENSE
Dynamic: author
Dynamic: author-email
Dynamic: classifier
Dynamic: description
Dynamic: description-content-type
Dynamic: home-page
Dynamic: license
Dynamic: summary
